tagCounter/__init__.py
tagCounter/tagCounter.py
lxgrcounter-0.4.dist-info/METADATA
lxgrcounter-0.4.dist-info/WHEEL
lxgrcounter-0.4.dist-info/top_level.txt
lxgrcounter-0.4.dist-info/RECORD
